{
  "publicPath": "",
  "all": [
    "client.bundle.js",
    "index.client.html"
  ],
  "initial": [
    "client.bundle.js"
  ],
  "async": [],
  "modules": {
    "e568c3fe": [
      0
    ],
    "7c299ccb": [
      0
    ],
    "80c0e610": [
      0
    ],
    "6b3c338e": [
      0
    ],
    "00ef5966": [
      0
    ],
    "5089a624": [
      0
    ],
    "714345a8": [
      0
    ],
    "7a64d9b2": [
      0
    ],
    "fea7bdae": [
      0
    ],
    "1ff19f28": [
      0
    ],
    "7c8c4934": [
      0
    ],
    "4f085e8d": [
      0
    ],
    "57c476b4": [
      0
    ],
    "7f853bc0": [
      0
    ],
    "51ca454d": [
      0
    ],
    "ef508f0c": [
      0
    ],
    "e0681ecc": [
      0
    ],
    "b979286a": [
      0
    ],
    "8f1ed1ac": [
      0
    ],
    "ee1f7888": [
      0
    ],
    "664dce70": [
      0
    ],
    "42548ced": [
      0
    ],
    "470db150": [
      0
    ],
    "5d0ea9f0": [
      0
    ],
    "7966ae8b": [
      0
    ],
    "710ac952": [
      0
    ],
    "e11a361e": [
      0
    ],
    "e488b1d8": [
      0
    ],
    "19ca7999": [
      0
    ],
    "13bbc39e": [
      0
    ],
    "7ac56424": [
      0
    ],
    "5d9cd17e": [
      0
    ],
    "5057ecc6": [
      0
    ],
    "bdeb7276": [
      0
    ],
    "d901cf3a": [
      0
    ],
    "705c2c56": [
      0
    ]
  }
}